DexeBotAsync/__init__.py
DexeBotAsync/aes.py
DexeBotAsync/api.py
DexeBotAsync/cosmetics.py
DexeBotAsync/enums.py
DexeBotAsync/exceptions.py
DexeBotAsync/http.py
DexeBotAsync-0.0.1.dist-info/METADATA
DexeBotAsync-0.0.1.dist-info/WHEEL
DexeBotAsync-0.0.1.dist-info/top_level.txt
DexeBotAsync-0.0.1.dist-info/RECORD
